op2_parser/__init__.py
op2_parser/cli.py
op2_parser/op2_parser.py
op2_parser/utils.py
op2_parser-0.3.0.dist-info/AUTHORS.rst
op2_parser-0.3.0.dist-info/LICENSE
op2_parser-0.3.0.dist-info/METADATA
op2_parser-0.3.0.dist-info/WHEEL
op2_parser-0.3.0.dist-info/RECORD
