Metadata-Version: 2.1
Name: op2_parser
Version: 0.3.0
Summary: Wrapper for pyNastran's op2 Parser
Author: Nicolas Cordier
Author-email: nicolas@cordier.io
Maintainer: Nicolas Cordier
Maintainer-email: nicolas@cordier.io
Requires-Python: >=3.11,<3.13
Classifier: Programming Language :: Python :: 3
Classifier: Programming Language :: Python :: 3.11
Classifier: Programming Language :: Python :: 3.12
Requires-Dist: click
Requires-Dist: levenshtein
Requires-Dist: numtools
Requires-Dist: pandas[performance]
Requires-Dist: pyNastran (>=1.3,<2.0)
